trajectopy_approx/__init__.py
trajectopy_approx/cubic_approximation.py
trajectopy_approx/math_utils.py
trajectopy_approx/mls_approximation.py
trajectopy_approx/rot_approximation.py
trajectopy_approx/settings.py
trajectopy_approx/voxelizer.py
trajectopy_approx-0.5.0.dist-info/LICENSE
trajectopy_approx-0.5.0.dist-info/METADATA
trajectopy_approx-0.5.0.dist-info/WHEEL
trajectopy_approx-0.5.0.dist-info/RECORD
