Metadata-Version: 2.1
Name: trajectopy-approx
Version: 0.5.0
Summary: Trajectory approximation using cubic polynomials
License: MIT
Author: Gereon Tombrink
Author-email: tombrink@igg.uni-bonn.de
Requires-Python: >=3.8.2,<3.12
Classifier: License :: OSI Approved :: MIT License
Classifier: Programming Language :: Python :: 3
Classifier: Programming Language :: Python :: 3.9
Classifier: Programming Language :: Python :: 3.10
Classifier: Programming Language :: Python :: 3.11
Requires-Dist: numpy (>=1.24.4)
Requires-Dist: pointset (>=0.1.5,<0.2.0)
Requires-Dist: rotationset (>=0.1.0,<0.2.0)
Requires-Dist: scipy (>=1.10.1)
Requires-Dist: spatialsorter (>=0.5.0,<0.6.0)
Requires-Dist: yaml-dataclass (>=0.1.3,<0.2.0)
